Workbook

Sheet README
A1: TCS (Tata Consultancy Services Ltd) — Financial Analytics Dataset
A2: Prepared for: Financial Analytics for Managers, FIIB — Dr Vibhav Pratap
A4: Company | B4: Tata Consultancy Services Ltd | NSE: TCS | BSE: 532540 | Tata Group flagship
A5: Statements | B5: Consolidated, Rs. crore, fiscal years ending 31 March (FY2015–FY2026); quarterly Sep-2023 to Sep-2026
A6: Source | B6: Source: Screener.in, TCS consolidated financials (data by C-MOTS), Rs. crore, accessed 23 Oct 2026. https://www.screener.in/company/TCS/consolidated/
A7: Market snapshot (22 Oct 2026) | B7: Price Rs 2,507 | Mkt cap Rs 9,07,736 cr | P/E 16.6 | Book value Rs 329 | Div yield 2.55% | 52-wk H/L 3,350 / 1,976 | Face value Rs 1
A9: Sheets
A10: Analysis | B10: Ratios computed with live Excel formulas (growth, margins, ROE, ROA, D/E, coverage, CFO/PAT, FCF margin, DuPont)
A11: Profit_Loss / Balance_Sheet / Cash_Flow | B11: Raw annual statements (blue = hardcoded source data)
A12: Ratios_Reported | B12: Debtor days, working-capital days, ROCE as published by the source
A13: Quarterly | B13: 13 quarters of P&L — good for trend/seasonality and simple forecasting exercises
A14: Shareholding | B14: Promoter / FII / DII / Public holding, 12 quarters
A16: Data notes
A17: 1 | B17: Other Income is negative in FY2026 (Rs -124 cr) and in Sep-25 / Dec-25 quarters — a one-off item worth discussing in class.
A18: 2 | B18: Equity capital roughly doubles in FY2019 because of a 1:1 bonus issue; EPS series is as reported.
A19: 3 | B19: Borrowings jump in FY2020 mainly from lease liabilities after Ind AS 116 — TCS is effectively debt-free; good teaching point for D/E.
A20: 4 | B20: Balance sheet ties: Equity + Reserves + Borrowings + Other Liabilities = Total = Fixed Assets + CWIP + Investments + Other Assets (checked for all years).
A21: 5 | B21: Daily share prices are not included. Pull them in Python: yfinance.download('TCS.NS', start='2015-04-01').
A23: Python | B23: pd.read_excel('TCS_Financial_Dataset.xlsx', sheet_name=None) or use TCS_financials_long.csv (tidy format)

Sheet Analysis
A1: TCS — Ratio Analysis (computed by formulas from the statement sheets)
A2: Black = formula. Edit the blue inputs on the statement sheets and everything here recalculates.
A4: Ratio | B4: FY2015 | C4: FY2016 | D4: FY2017 | E4: FY2018 | F4: FY2019 | G4: FY2020 | H4: FY2021 | I4: FY2022 | J4: FY2023 | K4: FY2024 | L4: FY2025 | M4: FY2026
A5: Growth
A6: Revenue growth (YoY) | B6: - | C6: =IFERROR(Profit_Loss!C5/Profit_Loss!B5-1,"-") -> 0.14789536 | D6: =IFERROR(Profit_Loss!D5/Profit_Loss!C5-1,"-") -> 0.085783186 | E6: =IFERROR(Profit_Loss!E5/Profit_Loss!D5-1,"-") -> 0.043554923 | F6: =IFERROR(Profit_Loss!F5/Profit_Loss!E5-1,"-") -> 0.18975013 | G6: =IFERROR(Profit_Loss!G5/Profit_Loss!F5-1,"-") -> 0.071594874 | H6: =IFERROR(Profit_Loss!H5/Profit_Loss!G5-1,"-") -> 0.046053177 | I6: =IFERROR(Profit_Loss!I5/Profit_Loss!H5-1,"-") -> 0.16797115 | J6: =IFERROR(Profit_Loss!J5/Profit_Loss!I5-1,"-") -> 0.17576687 | ... M6: =IFERROR(Profit_Loss!M5/Profit_Loss!L5-1,"-") -> 0.04581238
A7: Net profit growth (YoY) | B7: - | C7: =IFERROR(Profit_Loss!C13/Profit_Loss!B13-1,"-") -> 0.21326022 | D7: =IFERROR(Profit_Loss!D13/Profit_Loss!C13-1,"-") -> 0.082956693 | E7: =IFERROR(Profit_Loss!E13/Profit_Loss!D13-1,"-") -> -0.018097659 | F7: =IFERROR(Profit_Loss!F13/Profit_Loss!E13-1,"-") -> 0.21955178 | G7: =IFERROR(Profit_Loss!G13/Profit_Loss!F13-1,"-") -> 0.028040048 | H7: =IFERROR(Profit_Loss!H13/Profit_Loss!G13-1,"-") -> 0.0035442414 | I7: =IFERROR(Profit_Loss!I13/Profit_Loss!H13-1,"-") -> 0.18079356 | J7: =IFERROR(Profit_Loss!J13/Profit_Loss!I13-1,"-") -> 0.10023668 | ... M7: =IFERROR(Profit_Loss!M13/Profit_Loss!L13-1,"-") -> 0.013463942
A8: EPS growth (YoY) | B8: - | C8: =IFERROR(Profit_Loss!C14/Profit_Loss!B14-1,"-") -> 0.21507498 | D8: =IFERROR(Profit_Loss!D14/Profit_Loss!C14-1,"-") -> 0.083306268 | E8: =IFERROR(Profit_Loss!E14/Profit_Loss!D14-1,"-") -> 0.011242692 | F8: =IFERROR(Profit_Loss!F14/Profit_Loss!E14-1,"-") -> 0.24325526 | G8: =IFERROR(Profit_Loss!G14/Profit_Loss!F14-1,"-") -> 0.027661858 | H8: =IFERROR(Profit_Loss!H14/Profit_Loss!G14-1,"-") -> 0.017171366 | I8: =IFERROR(Profit_Loss!I14/Profit_Loss!H14-1,"-") -> 0.19482149 | J8: =IFERROR(Profit_Loss!J14/Profit_Loss!I14-1,"-") -> 0.099665871 | ... M8: =IFERROR(Profit_Loss!M14/Profit_Loss!L14-1,"-") -> 0.013487332
A9: Profitability
A10: EBITDA margin | B10: =Profit_Loss!B7/Profit_Loss!B5 -> 0.25866368 | C10: =Profit_Loss!C7/Profit_Loss!C5 -> 0.28235738 | D10: =Profit_Loss!D7/Profit_Loss!D5 -> 0.27390095 | E10: =Profit_Loss!E7/Profit_Loss!E5 -> 0.26413439 | F10: =Profit_Loss!F7/Profit_Loss!F5 -> 0.26973365 | G10: =Profit_Loss!G7/Profit_Loss!G5 -> 0.26829734 | H10: =Profit_Loss!H7/Profit_Loss!H5 -> 0.28351109 | I10: =Profit_Loss!I7/Profit_Loss!I5 -> 0.27669305 | ... M10: =Profit_Loss!M7/Profit_Loss!M5 -> 0.27113223
A11: Net profit margin | B11: =Profit_Loss!B13/Profit_Loss!B5 -> 0.2119432 | C11: =Profit_Loss!C13/Profit_Loss!C5 -> 0.22401193 | D11: =Profit_Loss!D13/Profit_Loss!D5 -> 0.22342878 | E11: =Profit_Loss!E13/Profit_Loss!E5 -> 0.21022875 | F11: =Profit_Loss!F13/Profit_Loss!F5 -> 0.2154947 | G11: =Profit_Loss!G13/Profit_Loss!G5 -> 0.20673595 | H11: =Profit_Loss!H13/Profit_Loss!H5 -> 0.19833472 | I11: =Profit_Loss!I13/Profit_Loss!I5 -> 0.20051211 | ... M11: =Profit_Loss!M13/Profit_Loss!M5 -> 0.18520641
A12: Return on equity (closing equity) | B12: =Profit_Loss!B13/(Balance_Sheet!B5+Balance_Sheet!B6) -> 0.39616866 | C12: =Profit_Loss!C13/(Balance_Sheet!C5+Balance_Sheet!C6) -> 0.34244147 | D12: =Profit_Loss!D13/(Balance_Sheet!D5+Balance_Sheet!D6) -> 0.30571601 | E12: =Profit_Loss!E13/(Balance_Sheet!E5+Balance_Sheet!E6) -> 0.30401278 | F12: =Profit_Loss!F13/(Balance_Sheet!F5+Balance_Sheet!F6) -> 0.35286094 | G12: =Profit_Loss!G13/(Balance_Sheet!G5+Balance_Sheet!G6) -> 0.38569527 | H12: =Profit_Loss!H13/(Balance_Sheet!H5+Balance_Sheet!H6) -> 0.37673111 | I12: =Profit_Loss!I13/(Balance_Sheet!I5+Balance_Sheet!I6) -> 0.43133757 | ... M12: =Profit_Loss!M13/(Balance_Sheet!M5+Balance_Sheet!M6) -> 0.46115256
A13: Return on assets (closing assets) | B13: =Profit_Loss!B13/Balance_Sheet!B14 -> 0.27360266 | C13: =Profit_Loss!C13/Balance_Sheet!C14 -> 0.27565664 | D13: =Profit_Loss!D13/Balance_Sheet!D14 -> 0.2575611 | E13: =Profit_Loss!E13/Balance_Sheet!E14 -> 0.24618077 | F13: =Profit_Loss!F13/Balance_Sheet!F14 -> 0.27710029 | G13: =Profit_Loss!G13/Balance_Sheet!G14 -> 0.2701058 | H13: =Profit_Loss!H13/Balance_Sheet!H14 -> 0.25049234 | I13: =Profit_Loss!I13/Balance_Sheet!I14 -> 0.272835 | ... M13: =Profit_Loss!M13/Balance_Sheet!M14 -> 0.27297466
A14: Efficiency & leverage
A15: Asset turnover (x) | B15: =Profit_Loss!B5/Balance_Sheet!B14 -> 1.2909245 | C15: =Profit_Loss!C5/Balance_Sheet!C14 -> 1.2305444 | D15: =Profit_Loss!D5/Balance_Sheet!D14 -> 1.152766 | E15: =Profit_Loss!E5/Balance_Sheet!E14 -> 1.1710138 | F15: =Profit_Loss!F5/Balance_Sheet!F14 -> 1.2858798 | G15: =Profit_Loss!G5/Balance_Sheet!G14 -> 1.3065256 | H15: =Profit_Loss!H5/Balance_Sheet!H14 -> 1.2629777 | I15: =Profit_Loss!I5/Balance_Sheet!I14 -> 1.3606909 | ... M15: =Profit_Loss!M5/Balance_Sheet!M14 -> 1.4738943
A16: Debt-to-equity (x) | B16: =Balance_Sheet!B7/(Balance_Sheet!B5+Balance_Sheet!B6) -> 0.0070702084 | C16: =Balance_Sheet!C7/(Balance_Sheet!C5+Balance_Sheet!C6) -> 0.0034472085 | D16: =Balance_Sheet!D7/(Balance_Sheet!D5+Balance_Sheet!D6) -> 0.0033521238 | E16: =Balance_Sheet!E7/(Balance_Sheet!E5+Balance_Sheet!E6) -> 0.002901513 | F16: =Balance_Sheet!F7/(Balance_Sheet!F5+Balance_Sheet!F6) -> 0.00069315565 | G16: =Balance_Sheet!G7/(Balance_Sheet!G5+Balance_Sheet!G6) -> 0.097163778 | H16: =Balance_Sheet!H7/(Balance_Sheet!H5+Balance_Sheet!H6) -> 0.090185462 | I16: =Balance_Sheet!I7/(Balance_Sheet!I5+Balance_Sheet!I6) -> 0.087705718 | ... M16: =Balance_Sheet!M7/(Balance_Sheet!M5+Balance_Sheet!M6) -> 0.10521261
A17: Interest coverage (EBIT/Interest, x) | B17: =IFERROR((Profit_Loss!B11+Profit_Loss!B9)/Profit_Loss!B9,"-") -> 253.86538 | C17: =IFERROR((Profit_Loss!C11+Profit_Loss!C9)/Profit_Loss!C9,"-") -> 965.84848 | D17: =IFERROR((Profit_Loss!D11+Profit_Loss!D9)/Profit_Loss!D9,"-") -> 1079.5312 | E17: =IFERROR((Profit_Loss!E11+Profit_Loss!E9)/Profit_Loss!E9,"-") -> 656.61538 | F17: =IFERROR((Profit_Loss!F11+Profit_Loss!F9)/Profit_Loss!F9,"-") -> 210.91414 | G17: =IFERROR((Profit_Loss!G11+Profit_Loss!G9)/Profit_Loss!G9,"-") -> 46.722944 | H17: =IFERROR((Profit_Loss!H11+Profit_Loss!H9)/Profit_Loss!H9,"-") -> 69.697017 | I17: =IFERROR((Profit_Loss!I11+Profit_Loss!I9)/Profit_Loss!I9,"-") -> 66.927296 | ... M17: =IFERROR((Profit_Loss!M11+Profit_Loss!M9)/Profit_Loss!M9,"-") -> 54.371638
A18: Cash flow quality
A19: CFO / Net profit (x) | B19: =Cash_Flow!B5/Profit_Loss!B13 -> 0.96555334 | C19: =Cash_Flow!C5/Profit_Loss!C13 -> 0.78515079 | D19: =Cash_Flow!D5/Profit_Loss!D13 -> 0.95697538 | E19: =Cash_Flow!E5/Profit_Loss!E13 -> 0.96858578 | F19: =Cash_Flow!F5/Profit_Loss!F13 -> 0.90593118 | G19: =Cash_Flow!G5/Profit_Loss!G13 -> 0.99759608 | H19: =Cash_Flow!H5/Profit_Loss!H13 -> 1.1916344 | I19: =Cash_Flow!I5/Profit_Loss!I13 -> 1.0390127 | ... M19: =Cash_Flow!M5/Profit_Loss!M13 -> 1.0533829
A20: FCF margin | B20: =Cash_Flow!B9/Profit_Loss!B5 -> 0.17354831 | C20: =Cash_Flow!C9/Profit_Loss!C5 -> 0.15779688 | D20: =Cash_Flow!D9/Profit_Loss!D5 -> 0.19726023 | E20: =Cash_Flow!E9/Profit_Loss!E5 -> 0.1889703 | F20: =Cash_Flow!F9/Profit_Loss!F5 -> 0.18066679 | G20: =Cash_Flow!G9/Profit_Loss!G5 -> 0.18656379 | H20: =Cash_Flow!H9/Profit_Loss!H5 -> 0.21722288 | I20: =Cash_Flow!I9/Profit_Loss!I5 -> 0.19287733 | ... M20: =Cash_Flow!M9/Profit_Loss!M5 -> 0.17980983
A21: DuPont check: margin × turnover × equity multiplier | B21: =(Profit_Loss!B13/Profit_Loss!B5)*(Profit_Loss!B5/Balance_Sheet!B14)*(Balance_Sheet!B14/(Balance_Sheet!B5+Balance_Sheet!B6)) -> 0.39616866 | C21: =(Profit_Loss!C13/Profit_Loss!C5)*(Profit_Loss!C5/Balance_Sheet!C14)*(Balance_Sheet!C14/(Balance_Sheet!C5+Balance_Sheet!C6)) -> 0.34244147 | D21: =(Profit_Loss!D13/Profit_Loss!D5)*(Profit_Loss!D5/Balance_Sheet!D14)*(Balance_Sheet!D14/(Balance_Sheet!D5+Balance_Sheet!D6)) -> 0.30571601 | E21: =(Profit_Loss!E13/Profit_Loss!E5)*(Profit_Loss!E5/Balance_Sheet!E14)*(Balance_Sheet!E14/(Balance_Sheet!E5+Balance_Sheet!E6)) -> 0.30401278 | F21: =(Profit_Loss!F13/Profit_Loss!F5)*(Profit_Loss!F5/Balance_Sheet!F14)*(Balance_Sheet!F14/(Balance_Sheet!F5+Balance_Sheet!F6)) -> 0.35286094 | G21: =(Profit_Loss!G13/Profit_Loss!G5)*(Profit_Loss!G5/Balance_Sheet!G14)*(Balance_Sheet!G14/(Balance_Sheet!G5+Balance_Sheet!G6)) -> 0.38569527 | H21: =(Profit_Loss!H13/Profit_Loss!H5)*(Profit_Loss!H5/Balance_Sheet!H14)*(Balance_Sheet!H14/(Balance_Sheet!H5+Balance_Sheet!H6)) -> 0.37673111 | I21: =(Profit_Loss!I13/Profit_Loss!I5)*(Profit_Loss!I5/Balance_Sheet!I14)*(Balance_Sheet!I14/(Balance_Sheet!I5+Balance_Sheet!I6)) -> 0.43133757 | ... M21: =(Profit_Loss!M13/Profit_Loss!M5)*(Profit_Loss!M5/Balance_Sheet!M14)*(Balance_Sheet!M14/(Balance_Sheet!M5+Balance_Sheet!M6)) -> 0.46115256

Sheet Profit_Loss
A1: TCS — Consolidated Profit & Loss (annual, FY ending March)
A2: Source: Screener.in, TCS consolidated financials (data by C-MOTS), Rs. crore, accessed 23 Oct 2026. https://www.screener.in/company/TCS/consolidated/
A4: Line item (Rs. crore) | B4: FY2015 | C4: FY2016 | D4: FY2017 | E4: FY2018 | F4: FY2019 | G4: FY2020 | H4: FY2021 | I4: FY2022 | J4: FY2023 | K4: FY2024 | L4: FY2025 | M4: FY2026
A5: Sales | B5: 94648 | C5: 108646 | D5: 117966 | E5: 123104 | F5: 146463 | G5: 156949 | H5: 164177 | I5: 191754 | J5: 225458 | K5: 240893 | L5: 255324 | M5: 267021
A6: Expenses | B6: 70167 | C6: 77969 | D6: 85655 | E6: 90588 | F6: 106957 | G6: 114840 | H6: 117631 | I6: 138697 | J6: 166199 | K6: 176597 | L6: 187917 | M6: 194623
A7: Operating Profit (EBITDA) | B7: 24482 | C7: 30677 | D7: 32311 | E7: 32516 | F7: 39506 | G7: 42109 | H7: 46546 | I7: 53057 | J7: 59259 | K7: 64296 | L7: 67407 | M7: 72398
A8: Other Income | B8: 3720 | C8: 3084 | D8: 4221 | E8: 3642 | F8: 4311 | G8: 4592 | H8: 1916 | I8: 4018 | J8: 3449 | K8: 3464 | L8: 3962 | M8: -124
A9: Interest | B9: 104 | C9: 33 | D9: 32 | E9: 52 | F9: 198 | G9: 924 | H9: 637 | I9: 784 | J9: 779 | K9: 778 | L9: 796 | M9: 1227
A10: Depreciation | B10: 1799 | C10: 1888 | D10: 1987 | E10: 2014 | F10: 2056 | G10: 3529 | H10: 4065 | I10: 4604 | J10: 5022 | K10: 4985 | L10: 5242 | M10: 5560
A11: Profit before Tax | B11: 26298 | C11: 31840 | D11: 34513 | E11: 34092 | F11: 41563 | G11: 42248 | H11: 43760 | I11: 51687 | J11: 56907 | K11: 61997 | L11: 65331 | M11: 65487
A12: Tax Rate (%) | B12: 24 | C12: 24 | D12: 24 | E12: 24 | F12: 24 | G12: 23 | H12: 26 | I12: 26 | J12: 26 | K12: 26 | L12: 25 | M12: 24
A13: Net Profit | B13: 20060 | C13: 24338 | D13: 26357 | E13: 25880 | F13: 31562 | G13: 32447 | H13: 32562 | I13: 38449 | J13: 42303 | K13: 46099 | L13: 48797 | M13: 49454
A14: EPS (Rs) | B14: 50.68 | C14: 61.58 | D14: 66.71 | E14: 67.46 | F14: 83.87 | G14: 86.19 | H14: 87.67 | I14: 104.75 | J14: 115.19 | K14: 126.88 | L14: 134.2 | M14: 136.01
A15: Dividend Payout (%) | B15: 78 | C15: 35 | D15: 35 | E15: 37 | F15: 36 | G15: 85 | H15: 43 | I15: 41 | J15: 100 | K15: 58 | L15: 94 | M15: 81

Sheet Balance_Sheet
A1: TCS — Consolidated Balance Sheet (as at 31 March)
A2: Source: Screener.in, TCS consolidated financials (data by C-MOTS), Rs. crore, accessed 23 Oct 2026. https://www.screener.in/company/TCS/consolidated/
A4: Line item (Rs. crore) | B4: FY2015 | C4: FY2016 | D4: FY2017 | E4: FY2018 | F4: FY2019 | G4: FY2020 | H4: FY2021 | I4: FY2022 | J4: FY2023 | K4: FY2024 | L4: FY2025 | M4: FY2026
A5: Equity Capital | B5: 196 | C5: 197 | D5: 197 | E5: 191 | F5: 375 | G5: 375 | H5: 370 | I5: 366 | J5: 366 | K5: 362 | L5: 362 | M5: 362
A6: Reserves | B6: 50439 | C6: 70875 | D6: 86017 | E6: 84937 | F6: 89071 | G6: 83751 | H6: 86063 | I6: 88773 | J6: 90058 | K6: 90127 | L6: 94394 | M6: 106878
A7: Borrowings | B7: 358 | C7: 245 | D7: 289 | E7: 247 | F7: 62 | G7: 8174 | H7: 7795 | I7: 7818 | J7: 7688 | K7: 8021 | L7: 9392 | M7: 11283
A8: Other Liabilities | B8: 22325 | C8: 16974 | D8: 15830 | E8: 19751 | F8: 24393 | G8: 27827 | H8: 35764 | I8: 43967 | J8: 44747 | K8: 46962 | L8: 54501 | M8: 62644
A9: Total Liabilities | B9: 73318 | C9: 88291 | D9: 102333 | E9: 105126 | F9: 113901 | G9: 120127 | H9: 129992 | I9: 140924 | J9: 142859 | K9: 145472 | L9: 158649 | M9: 181167
A10: Fixed Assets | B10: 11638 | C10: 11774 | D10: 11701 | E10: 11973 | F10: 12290 | G10: 20928 | H10: 21021 | I10: 21298 | J10: 20515 | K10: 19604 | L10: 23053 | M10: 31343
A11: CWIP | B11: 2766 | C11: 1670 | D11: 1541 | E11: 1278 | F11: 963 | G11: 906 | H11: 926 | I11: 1205 | J11: 1234 | K11: 1564 | L11: 1546 | M11: 2665
A12: Investments | B12: 1662 | C12: 22822 | D12: 41980 | E12: 36008 | F12: 29330 | G12: 26356 | H12: 29373 | I12: 30485 | J12: 37163 | K12: 31762 | L12: 30964 | M12: 33988
A13: Other Assets | B13: 57252 | C13: 52025 | D13: 47111 | E13: 55867 | F13: 71318 | G13: 71937 | H13: 78672 | I13: 87936 | J13: 83947 | K13: 92542 | L13: 103086 | M13: 113171
A14: Total Assets | B14: 73318 | C14: 88291 | D14: 102333 | E14: 105126 | F14: 113901 | G14: 120127 | H14: 129992 | I14: 140924 | J14: 142859 | K14: 145472 | L14: 158649 | M14: 181167

Sheet Cash_Flow
A1: TCS — Consolidated Cash Flow Statement (annual)
A2: Source: Screener.in, TCS consolidated financials (data by C-MOTS), Rs. crore, accessed 23 Oct 2026. https://www.screener.in/company/TCS/consolidated/
A4: Line item (Rs. crore) | B4: FY2015 | C4: FY2016 | D4: FY2017 | E4: FY2018 | F4: FY2019 | G4: FY2020 | H4: FY2021 | I4: FY2022 | J4: FY2023 | K4: FY2024 | L4: FY2025 | M4: FY2026
A5: Cash from Operating Activity | B5: 19369 | C5: 19109 | D5: 25223 | E5: 25067 | F5: 28593 | G5: 32369 | H5: 38802 | I5: 39949 | J5: 41965 | K5: 44338 | L5: 48908 | M5: 52094
A6: Cash from Investing Activity | B6: -1807 | C6: -5010 | D6: -16895 | E6: 3104 | F6: 1645 | G6: 8968 | H6: -7956 | I6: -738 | J6: 548 | K6: 6091 | L6: -2144 | M6: -11886
A7: Cash from Financing Activity | B7: -17168 | C7: -9666 | D7: -11026 | E7: -26885 | F7: -27897 | G7: -39915 | H7: -32634 | I7: -33581 | J7: -47878 | K7: -48536 | L7: -47438 | M7: -42133
A8: Net Cash Flow | B8: 394 | C8: 4433 | D8: -2698 | E8: 1286 | F8: 2341 | G8: 1422 | H8: -1788 | I8: 5630 | J8: -5365 | K8: 1893 | L8: -674 | M8: -1925
A9: Free Cash Flow | B9: 16426 | C9: 17144 | D9: 23270 | E9: 23263 | F9: 26461 | G9: 29281 | H9: 35663 | I9: 36985 | J9: 38902 | K9: 41688 | L9: 44994 | M9: 48013

Sheet Sheet1
A1: TCS — Descriptive Statistics, Annual (FY2015–FY2026)
A2: All cells are formulas linked to the statement and Analysis sheets. Growth rates use FY2016–FY2026 (11 obs.).
A4: A. Levels
A5: Statistic | B5: Sales | C5: Expenses | D5: Operating Profit (EBITDA)
A6: Count (N) | B6: =COUNT(Profit_Loss!B5:M5) -> 12 | C6: =COUNT(Profit_Loss!$B6:$M6) -> 12 | D6: =COUNT(Profit_Loss!$B7:$M7) -> 12
A7: Mean | B7: =AVERAGE(Profit_Loss!B5:M5) -> 174366.92 | C7: =AVERAGE(Profit_Loss!B6:M6) -> 127320 | D7: =AVERAGE(Profit_Loss!B7:M7) -> 47047
A8: Median | B8: =MEDIAN(Profit_Loss!B5:M5) -> 160563 | C8: =MEDIAN(Profit_Loss!B6:M6) -> 116235.5
A9: Standard deviation (sample) | B9: =_xlfn.STDEV.S(Profit_Loss!B5:M5) -> 60412.445 | C9: =_xlfn.STDEV.S(Profit_Loss!B6:M6) -> 44438.316
A10: Minimum | B10: =MIN(Profit_Loss!B5:M5) -> 94648 | C10: =MIN(Profit_Loss!B6:M6) -> 70167
A11: 1st quartile (Q1) | B11: =QUARTILE(Profit_Loss!B5:M5,1) -> 121819.5 | C11: =QUARTILE(Profit_Loss!B6:M6,1) -> 89354.75
A12: 3rd quartile (Q3) | B12: =QUARTILE(Profit_Loss!B5:M5,3) -> 229316.75 | C12: =QUARTILE(Profit_Loss!B6:M6,3) -> 168798.5
A13: Maximum | B13: =MAX(Profit_Loss!B5:M5) -> 267021 | C13: =MAX(Profit_Loss!B6:M6) -> 194623
A14: Range | B14: =B13-B10 -> 172373 | C14: =C13-C10 -> 124456 | D14: =D13-D10 -> 0 | E14: =E13-E10 -> 0 | F14: =F13-F10 -> 0 | G14: =G13-G10 -> 0 | H14: =H13-H10 -> 0 | I14: =I13-I10 -> 0 | J14: =J13-J10 -> 0
A15: Interquartile range (IQR) | B15: =B12-B11 -> 107497.25 | C15: =C12-C11 -> 79443.75 | D15: =D12-D11 -> 0 | E15: =E12-E11 -> 0 | F15: =F12-F11 -> 0 | G15: =G12-G11 -> 0 | H15: =H12-H11 -> 0 | I15: =I12-I11 -> 0 | J15: =J12-J11 -> 0
A16: Coefficient of variation | B16: =(B9/B7)*100 -> 34.646736 | C16: =(C9/C7)*100 -> 34.902856 | D16: =(D9/D7)*100 -> 0 | E16: =(E9/E7)*100 -> #DIV/0! | F16: =(F9/F7)*100 -> #DIV/0! | G16: =(G9/G7)*100 -> #DIV/0! | H16: =(H9/H7)*100 -> #DIV/0! | I16: =(I9/I7)*100 -> #DIV/0! | J16: =(J9/J7)*100 -> #DIV/0!
A17: Skewness | B17: =SKEW(Profit_Loss!B5:M5) -> 0.30991481 | C17: =SKEW(Profit_Loss!B6:M6) -> 0.33216438
A18: Excess kurtosis | B18: =KURT(Profit_Loss!B5:M5) -> -1.431647 | C18: =KURT(Profit_Loss!B6:M6) -> -1.4537287
A19: CAGR (first to last period) | B19: =((Profit_Loss!M5/Profit_Loss!B5)^1/12)-1 -> -0.76489995 | C19: =((Profit_Loss!$M6/Profit_Loss!$B6)^1/12)-1 -> -0.76885739 | D19: =((Profit_Loss!$M7/Profit_Loss!$B7)^1/12)-1 -> -0.75356725 | E19: =((Profit_Loss!$M8/Profit_Loss!$B8)^1/12)-1 -> -1.0027778 | F19: =((Profit_Loss!$M9/Profit_Loss!$B9)^1/12)-1 -> -0.016826923 | G19: =((Profit_Loss!$M10/Profit_Loss!$B10)^1/12)-1 -> -0.74244951 | H19: =((Profit_Loss!$M11/Profit_Loss!$B11)^1/12)-1 -> -0.79248422 | I19: =((Profit_Loss!$M12/Profit_Loss!$B12)^1/12)-1 -> -0.91666667 | J19: =((Profit_Loss!$M13/Profit_Loss!$B13)^1/12)-1 -> -0.79455799
A21: B. Ratios & growth rates
A22: Statistic | B22: Debtor Days | C22: Working Capital Days | D22: ROCE (%)
A23: Count (N) | B23: =COUNT(Ratios_Reported!$B5:$M5) -> 12 | C23: =COUNT(Ratios_Reported!$B6:$M6) -> 12 | D23: =COUNT(Ratios_Reported!$B7:$M7) -> 12
A24: Mean | B24: =AVERAGE(Ratios_Reported!B5:M5) -> 77.416667 | C24: =AVERAGE(Ratios_Reported!B6:M6) -> 48.333333 | D24: =AVERAGE(Ratios_Reported!B7:M7) -> 52.666667
A25: Median | B25: =MEDIAN(Ratios_Reported!B5:M5) -> 79.5 | C25: =MEDIAN(Ratios_Reported!B6:M6) -> 48.5 | D25: =MEDIAN(Ratios_Reported!B7:M7) -> 50.5
A26: Standard deviation (sample) | B26: =_xlfn.STDEV.S(Ratios_Reported!B5:M5) -> 7.6212422 | C26: =_xlfn.STDEV.S(Ratios_Reported!B6:M6) -> 15.628257 | D26: =_xlfn.STDEV.S(Ratios_Reported!B7:M7) -> 8.4135533
A27: Minimum | B27: =MIN(Ratios_Reported!B5:M5) -> 67 | C27: =MIN(Ratios_Reported!B6:M6) -> 30 | D27: =MIN(Ratios_Reported!B7:M7) -> 39
A28: 1st quartile (Q1) | B28: =QUARTILE(Ratios_Reported!B5:M5,1) -> 70.75 | C28: =QUARTILE(Ratios_Reported!B6:M6,1) -> 33.75 | D28: =QUARTILE(Ratios_Reported!B7:M7,1) -> 47
A29: 3rd quartile (Q3) | B29: =QUARTILE(Ratios_Reported!B5:M5,3) -> 81 | C29: =QUARTILE(Ratios_Reported!B6:M6,3) -> 62 | D29: =QUARTILE(Ratios_Reported!B7:M7,3) -> 60
A30: Maximum | B30: =MAX(Ratios_Reported!B5:M5) -> 93 | C30: =MAX(Ratios_Reported!B6:M6) -> 70 | D30: =MAX(Ratios_Reported!B7:M7) -> 65
A31: Range | B31: =B30-B27 -> 26 | C31: =C30-C27 -> 40 | D31: =D30-D27 -> 26
A32: Interquartile range (IQR) | B32: =B29-B28 -> 10.25 | C32: =C29-C28 -> 28.25 | D32: =D29-D28 -> 13
A33: Coefficient of variation | B33: =(B26/B24)*100 -> 9.8444464 | C33: =(C26/C24)*100 -> 32.334325 | D33: =(D26/D24)*100 -> 15.975101
A34: Skewness | B34: =SKEW(Ratios_Reported!B5:M5) -> 0.38234829 | C34: =SKEW(Ratios_Reported!B6:M6) -> 0.057241864 | D34: =SKEW(Ratios_Reported!B7:M7) -> 0.19253019
A35: Excess kurtosis | B35: =KURT(Ratios_Reported!B5:M5) -> -0.021661936 | C35: =KURT(Ratios_Reported!B6:M6) -> -2.1620507 | D35: =KURT(Ratios_Reported!B7:M7) -> -1.0308823

Sheet Ratios_Reported
A1: TCS — Efficiency ratios as reported by source
A2: Source: Screener.in, TCS consolidated financials (data by C-MOTS), Rs. crore, accessed 23 Oct 2026. https://www.screener.in/company/TCS/consolidated/
A4: Line item (Rs. crore) | B4: FY2015 | C4: FY2016 | D4: FY2017 | E4: FY2018 | F4: FY2019 | G4: FY2020 | H4: FY2021 | I4: FY2022 | J4: FY2023 | K4: FY2024 | L4: FY2025 | M4: FY2026
A5: Debtor Days | B5: 79 | C5: 81 | D5: 70 | E5: 74 | F5: 68 | G5: 71 | H5: 67 | I5: 80 | J5: 81 | K5: 81 | L5: 84 | M5: 93
A6: Working Capital Days | B6: 33 | C6: 62 | D6: 62 | E6: 61 | F6: 70 | G6: 64 | H6: 59 | I6: 33 | J6: 30 | K6: 34 | L6: 34 | M6: 38
A7: ROCE (%) | B7: 50 | C7: 51 | D7: 44 | E7: 39 | F7: 47 | G7: 47 | H7: 49 | I7: 54 | J7: 59 | K7: 64 | L7: 65 | M7: 63

Sheet Quarterly
A1: TCS — Consolidated Quarterly Results (quarter ending)
A2: Source: Screener.in, TCS consolidated financials (data by C-MOTS), Rs. crore, accessed 23 Oct 2026. https://www.screener.in/company/TCS/consolidated/
A4: Line item (Rs. crore) | B4: Sep-23 | C4: Dec-23 | D4: Mar-24 | E4: Jun-24 | F4: Sep-24 | G4: Dec-24 | H4: Mar-25 | I4: Jun-25 | J4: Sep-25 | K4: Dec-25 | L4: Mar-26 | M4: Jun-26 | N4: Sep-26
A5: Sales | B5: 59692 | C5: 60583 | D5: 61237 | E5: 62613 | F5: 64259 | G5: 63973 | H5: 64479 | I5: 63437 | J5: 65799 | K5: 67087 | L5: 70698 | M5: 72275 | N5: 73188
A6: Expenses | B6: 43946 | C6: 44195 | D6: 44073 | E6: 45951 | F6: 47528 | G6: 46939 | H6: 47499 | I6: 46562 | J6: 47821 | K6: 48818 | L6: 51422 | M6: 53719 | N6: 54373
A7: Operating Profit | B7: 15746 | C7: 16388 | D7: 17164 | E7: 16662 | F7: 16731 | G7: 17034 | H7: 16980 | I7: 16875 | J7: 17978 | K7: 18269 | L7: 19276 | M7: 18556 | N7: 18815
A8: Other Income | B8: 1006 | C8: -96 | D8: 1157 | E8: 962 | F8: 729 | G8: 1243 | H8: 1028 | I8: 1660 | J8: -268 | K8: -2273 | L8: 757 | M8: 900 | N8: 1337
A9: Interest | B9: 159 | C9: 230 | D9: 226 | E9: 173 | F9: 162 | G9: 234 | H9: 227 | I9: 195 | J9: 229 | K9: 538 | L9: 265 | M9: 273 | N9: 252
A10: Depreciation | B10: 1263 | C10: 1233 | D10: 1246 | E10: 1220 | F10: 1266 | G10: 1377 | H10: 1379 | I10: 1361 | J10: 1413 | K10: 1380 | L10: 1406 | M10: 1239 | N10: 1262
A11: Profit before Tax | B11: 15330 | C11: 14829 | D11: 16849 | E11: 16231 | F11: 16032 | G11: 16666 | H11: 16402 | I11: 16979 | J11: 16068 | K11: 14078 | L11: 18362 | M11: 17944 | N11: 18638
A12: Net Profit | B12: 11380 | C12: 11097 | D12: 12502 | E12: 12105 | F12: 11955 | G12: 12444 | H12: 12293 | I12: 12819 | J12: 12131 | K12: 10720 | L12: 13784 | M12: 13420 | N12: 13934
A13: EPS (Rs) | B13: 31 | C13: 30.56 | D13: 34.37 | E13: 33.28 | F13: 32.92 | G13: 34.22 | H13: 33.79 | I13: 35.27 | J13: 33.37 | K13: 29.45 | L13: 37.92 | M13: 36.9 | N13: 38.37

Sheet Shareholding
A1: TCS — Shareholding Pattern (quarter ending, %)
A2: Source: Screener.in, TCS consolidated financials (data by C-MOTS), Rs. crore, accessed 23 Oct 2026. https://www.screener.in/company/TCS/consolidated/
A4: Line item (Rs. crore) | B4: Dec-23 | C4: Mar-24 | D4: Jun-24 | E4: Sep-24 | F4: Dec-24 | G4: Mar-25 | H4: Jun-25 | I4: Sep-25 | J4: Dec-25 | K4: Mar-26 | L4: Jun-26 | M4: Sep-26
A5: Promoters (%) | B5: 72.41 | C5: 71.77 | D5: 71.77 | E5: 71.77 | F5: 71.77 | G5: 71.77 | H5: 71.77 | I5: 71.77 | J5: 71.77 | K5: 71.77 | L5: 71.77 | M5: 71.77
A6: FIIs (%) | B6: 12.46 | C6: 12.7 | D6: 12.35 | E6: 12.66 | F6: 12.68 | G6: 12.04 | H6: 11.48 | I6: 10.33 | J6: 10.37 | K6: 9.66 | L6: 9.07 | M6: 9.01
A7: DIIs (%) | B7: 10.03 | C7: 10.61 | D7: 11 | E7: 10.86 | F7: 10.86 | G7: 11.49 | H7: 11.95 | I7: 12.64 | J7: 12.81 | K7: 13.34 | L7: 13.41 | M7: 13.57
A8: Government (%) | B8: 0.05 | C8: 0.06 | D8: 0.06 | E8: 0.06 | F8: 0.06 | G8: 0.06 | H8: 0.06 | I8: 0.06 | J8: 0.06 | K8: 0.06 | L8: 0.06 | M8: 0
A9: Public (%) | B9: 5.03 | C9: 4.86 | D9: 4.82 | E9: 4.66 | F9: 4.63 | G9: 4.63 | H9: 4.77 | I9: 5.21 | J9: 4.98 | K9: 5.16 | L9: 5.69 | M9: 5.66
A10: No. of Shareholders | B10: 2336016 | C10: 2203209 | D10: 2181391 | E10: 2093962 | F10: 2075117 | G10: 2115093 | H10: 2164289 | I10: 2388232 | J10: 2332275 | K10: 2450090 | L10: 2605182 | M10: 2579099
